[
    {
        "uuid": "42c507d6-5068-46c6-a74d-68d541e81873",
        "duration_in_minutes": 111,
        "narrator": "\u0406\u0432\u0430\u043d \u0406\u0432\u0430\u043d\u043e\u0432",
        "file_url": "http:\/\/localhost\/mock-file",
        "price": 370,
        "discount_percent": 0,
        "discount_price": 370,
        "sales_count": 916,
        "book_slug": "gamlet"
    },
    {
        "uuid": "6637d819-af66-44fa-83df-c38760414fb9",
        "duration_in_minutes": 111,
        "narrator": "\u0406\u0432\u0430\u043d \u0406\u0432\u0430\u043d\u043e\u0432",
        "file_url": "http:\/\/localhost\/mock-file",
        "price": 370,
        "discount_percent": 0,
        "discount_price": 370,
        "sales_count": 916,
        "book_slug": "romeo-i-dzhuljetta"
    },
    {
        "uuid": "c1db4f80-b317-4d2a-9c2c-4ad88cf89aec",
        "duration_in_minutes": 111,
        "narrator": "\u0406\u0432\u0430\u043d \u0406\u0432\u0430\u043d\u043e\u0432",
        "file_url": "http:\/\/localhost\/mock-file",
        "price": 370,
        "discount_percent": 0,
        "discount_price": 370,
        "sales_count": 916,
        "book_slug": "sobaka-baskerviley"
    },
    {
        "uuid": "1fd4c94d-3d1e-4e4c-96c1-ded51b76f341",
        "duration_in_minutes": 111,
        "narrator": "\u0406\u0432\u0430\u043d \u0406\u0432\u0430\u043d\u043e\u0432",
        "file_url": "http:\/\/localhost\/mock-file",
        "price": 370,
        "discount_percent": 0,
        "discount_price": 370,
        "sales_count": 916,
        "book_slug": "syayvo"
    },
    {
        "uuid": "aa97bde4-6acb-4fe2-8ef3-c5fc5603ac2b",
        "duration_in_minutes": 111,
        "narrator": "\u0406\u0432\u0430\u043d \u0406\u0432\u0430\u043d\u043e\u0432",
        "file_url": "http:\/\/localhost\/mock-file",
        "price": 370,
        "discount_percent": 0,
        "discount_price": 370,
        "sales_count": 916,
        "book_slug": "velikiy-getsbi"
    }
]